docs/Makefile
docs/api_reference.rst
docs/conf.py
docs/contributing.rst
docs/examples.rst
docs/history.rst
docs/index.rst
docs/make.bat
docs/readme.rst
docs/modules/mesh2scattering.input.rst
docs/modules/mesh2scattering.numcalc.rst
docs/modules/mesh2scattering.output.rst
docs/modules/mesh2scattering.process.rst
docs/modules/mesh2scattering.utils.rst
mesh2scattering/__init__.py
mesh2scattering/input/EvaluationGrid.py
mesh2scattering/input/SampleMesh.py
mesh2scattering/input/SoundSource.py
mesh2scattering/input/__init__.py
mesh2scattering/input/input.py
mesh2scattering/numcalc/__init__.py
mesh2scattering/numcalc/numcalc.py
mesh2scattering/numcalc/bin/readme.txt
mesh2scattering/numcalc/src/Makefile
mesh2scattering/numcalc/src/NC_3dFunctions.cpp
mesh2scattering/numcalc/src/NC_Addresses.cpp
mesh2scattering/numcalc/src/NC_Arrays.h
mesh2scattering/numcalc/src/NC_CommonFunctions.cpp
mesh2scattering/numcalc/src/NC_ConstantsVariables.h
mesh2scattering/numcalc/src/NC_EquationSystem.cpp
mesh2scattering/numcalc/src/NC_Input.cpp
mesh2scattering/numcalc/src/NC_IntegrationConstants.h
mesh2scattering/numcalc/src/NC_Macros.h
mesh2scattering/numcalc/src/NC_Main.cpp
mesh2scattering/numcalc/src/NC_PostProcessing.cpp
mesh2scattering/numcalc/src/NC_TypeDefinition.h
mesh2scattering/output/__init__.py
mesh2scattering/output/output.py
mesh2scattering/process/__init__.py
mesh2scattering/process/coefficients.py
mesh2scattering/process/process.py
mesh2scattering/utils/__init__.py
mesh2scattering/utils/utils.py
mesh2scattering-1.0.2.dist-info/licenses/LICENSE.txt
tests/conftest.py
tests/test_input.py
tests/test_input_EvaluationGrid.py
tests/test_input_SampleMesh.py
tests/test_input_SoundSource.py
tests/test_mesh2scattering.py
tests/test_numcalc.py
tests/test_output.py
tests/test_process.py
tests/test_scattering.py
tests/test_utils.py
tests/test_write_read_projects.py
tests/references/Grid/Elements.txt
tests/references/Grid/Nodes.txt
tests/references/Grid/sample.stl
tests/references/Mesh/Elements.txt
tests/references/Mesh/Nodes.txt
mesh2scattering-1.0.2.dist-info/METADATA
mesh2scattering-1.0.2.dist-info/WHEEL
mesh2scattering-1.0.2.dist-info/top_level.txt
mesh2scattering-1.0.2.dist-info/RECORD
