Metadata-Version: 2.4
Name: mesh2scattering
Version: 1.0.2
Summary: Numerical calculation of surface scattering.
License:                       EUROPEAN UNION PUBLIC LICENCE v. 1.2
Project-URL: Tracker, https://github.com/ahms5/mesh2scattering/issues
Project-URL: Documentation, https://mesh2scattering.readthedocs.io/
Project-URL: Download, https://pypi.org/project/mesh2scattering/
Project-URL: Source, https://github.com/ahms5/mesh2scattering
Project-URL: Changelog, https://github.com/ahms5/mesh2scattering/blob/master/CHANGELOG.md
Keywords: acoustics,pyfar
Classifier: Development Status :: 4 - Beta
Classifier: Intended Audience :: Science/Research
Classifier: License :: OSI Approved :: MIT License
Classifier: Natural Language :: English
Classifier: Programming Language :: Python :: 3
Classifier: Programming Language :: Python :: 3.9
Classifier: Programming Language :: Python :: 3.10
Classifier: Programming Language :: Python :: 3.11
Classifier: Programming Language :: Python :: 3.12
Classifier: Programming Language :: Python :: 3.13
Requires-Python: >=3.9
License-File: LICENSE.txt
Requires-Dist: numpy>=1.14.0
Requires-Dist: scipy>=1.5.0
Requires-Dist: matplotlib
Requires-Dist: pyfar<0.8.0
Requires-Dist: psutil
Requires-Dist: sofar
Requires-Dist: trimesh
Requires-Dist: pooch
Provides-Extra: deploy
Requires-Dist: twine; extra == "deploy"
Requires-Dist: wheel; extra == "deploy"
Requires-Dist: build; extra == "deploy"
Requires-Dist: setuptools; extra == "deploy"
Requires-Dist: bump-my-version; extra == "deploy"
Provides-Extra: tests
Requires-Dist: pytest; extra == "tests"
Requires-Dist: pytest-cov; extra == "tests"
Requires-Dist: watchdog; extra == "tests"
Requires-Dist: ruff==0.9.8; extra == "tests"
Requires-Dist: coverage; extra == "tests"
Requires-Dist: nbmake>=0.7.0; extra == "tests"
Provides-Extra: docs
Requires-Dist: sphinx; extra == "docs"
Requires-Dist: autodocsumm>=0.2.14; extra == "docs"
Requires-Dist: pydata-sphinx-theme; extra == "docs"
Requires-Dist: sphinx_mdinclude; extra == "docs"
Requires-Dist: sphinx-design; extra == "docs"
Requires-Dist: sphinx-favicon; extra == "docs"
Requires-Dist: sphinx-reredirects; extra == "docs"
Requires-Dist: nbsphinx; extra == "docs"
Requires-Dist: sphinx_gallery; extra == "docs"
Requires-Dist: nbsphinx_link; extra == "docs"
Requires-Dist: ipython; extra == "docs"
Provides-Extra: dev
Requires-Dist: mesh2scattering[deploy,docs,tests]; extra == "dev"
Dynamic: license-file
